{
  "doc_id": "usfed.fr.2015-15956",
  "doc_family_id": "usfed.fr.2015-15956",
  "title": "Loans in Areas Having Special Flood Hazards",
  "short_title": "2015-15956",
  "slug": "2015-15956",
  "title_normalized": "Loans in Areas Having Special Flood Hazards",
  "regulator": "Federal Reserve System",
  "regulator_acronym": "FRS",
  "jurisdiction": "United States",
  "document_class": "Final Rule",
  "publication_type": "Final Rule",
  "publication_type_normalized": "Final Rule",
  "authority_class": "primary_normative",
  "authority_level": "binding_regulation",
  "nova_tier": 2,
  "prudential_weight": 0.7,
  "status": "active",
  "heading_path": [
    "Federal Reserve System",
    "Federal Register",
    "Final Rule",
    "2015-15956"
  ],
  "section_path": "Federal Reserve System > Federal Register > Final Rule > 2015-15956",
  "structural_level": "document",
  "normative_weight": "mandatory",
  "current_version_flag": true,
  "is_primary_normative": true,
  "is_supporting_interpretive": false,
  "is_context_only": false,
  "paragraph_role": "scope_statement",
  "contains_definition": false,
  "contains_formula": false,
  "contains_requirement": true,
  "contains_deadline": true,
  "contains_parameter": false,
  "contains_assignment": false,
  "is_appendix": false,
  "depth": 0,
  "version_id": "2015-07-21",
  "version_label": "2015",
  "citation_anchor": "#fr-2015-15956",
  "document_number": "2015-15956",
  "citation": "80 FR 43216",
  "publication_date": "2015-07-21",
  "effective_date_start": "2015-10-01",
  "effective_date_end": null,
  "abstract": "The Office of the Comptroller of the Currency (OCC), Board of Governors of the Federal Reserve System (Board), Federal Deposit Insurance Corporation (FDIC), the Farm Credit Administration (FCA), and the National Credit Union Administration (NCUA) (collectively, the Agencies) are amending their regulations regarding loans in areas having special flood hazards to implement certain provisions of the Homeowner Flood Insurance Affordability Act of 2014 (HFIAA), which amends some of the changes to the Flood Disaster Protection Act of 1973 mandated by the Biggert-Waters Flood Insurance Reform Act of 2012 (Biggert-Waters). Specifically, the final rule requires the escrow of flood insurance payments on residential improved real estate securing a loan, consistent with the changes set forth in HFIAA. The final rule also incorporates an exemption in HFIAA for certain detached structures from the mandatory flood insurance purchase requirement. Furthermore, the final rule implements the provisions of Biggert-Waters related to the force placement of flood insurance. Finally, the final rule integrates the OCC's flood insurance regulations for national banks and Federal savings associations. The Agencies plan to address the private flood insurance provisions in Biggert-Waters in a separate rulemaking.",
  "action": "Final rule.",
  "html_url": "https://www.federalregister.gov/documents/2015/07/21/2015-15956/loans-in-areas-having-special-flood-hazards",
  "body_html_url": "https://www.federalregister.gov/documents/full_text/html/2015/07/21/2015-15956.html",
  "pdf_url": "https://www.govinfo.gov/content/pkg/FR-2015-07-21/pdf/2015-15956.pdf",
  "cfr_references": [
    {
      "chapter": null,
      "citation_url": null,
      "part": 22,
      "title": 12
    },
    {
      "chapter": null,
      "citation_url": null,
      "part": 172,
      "title": 12
    },
    {
      "chapter": null,
      "citation_url": null,
      "part": 208,
      "title": 12
    },
    {
      "chapter": null,
      "citation_url": null,
      "part": 339,
      "title": 12
    },
    {
      "chapter": null,
      "citation_url": null,
      "part": 614,
      "title": 12
    },
    {
      "chapter": null,
      "citation_url": null,
      "part": 760,
      "title": 12
    }
  ],
  "docket_ids": [
    "Docket ID OCC-2014-0016",
    "Regulation H, Docket No. R-1498"
  ],
  "regulation_id_numbers": [
    "1557-AD84",
    "3052-AC93",
    "3064-AE27",
    "3133-AE40",
    "7100 AE22"
  ],
  "page_length": 48,
  "issuing_agency": "Board of Governors of the Federal Reserve System",
  "issuing_division": "Board of Governors",
  "document_date_iso": "2015-07-21",
  "document_date_raw": "2015-07-21",
  "word_count_raw_body": 57448,
  "section_headings": [],
  "toc_depth": 0,
  "has_appendices": false,
  "has_tables": false,
  "table_count": 0,
  "has_footnotes": false,
  "footnote_count": 0,
  "inline_cross_references": [
    "{'chapter': None, 'citation_url': None, 'part': 22, 'title': 12}",
    "{'chapter': None, 'citation_url': None, 'part': 172, 'title': 12}",
    "{'chapter': None, 'citation_url': None, 'part': 208, 'title': 12}",
    "{'chapter': None, 'citation_url': None, 'part': 339, 'title': 12}",
    "{'chapter': None, 'citation_url': None, 'part': 614, 'title': 12}",
    "{'chapter': None, 'citation_url': None, 'part': 760, 'title': 12}"
  ],
  "include_in_primary_corpus": true,
  "include_in_context_corpus": true,
  "include_in_support_corpus": false,
  "applies_to_state_member_banks": false,
  "applies_to_bank_holding_companies": false,
  "applies_to_savings_loan_holding": false,
  "applies_to_foreign_banking_orgs": false,
  "applies_to_nonbank_financial": false,
  "applies_to_insured_depository": true,
  "superseded_by_doc_id": null,
  "supersedes_doc_id": null,
  "correction_of": null,
  "corrections": [],
  "is_correction": false,
  "has_corrections": false,
  "start_page": 43216,
  "end_page": 43263,
  "content_source": "Federal Register API",
  "source_url": "https://www.federalregister.gov/documents/2015/07/21/2015-15956/loans-in-areas-having-special-flood-hazards",
  "source_html_url": "https://www.federalregister.gov/documents/2015/07/21/2015-15956/loans-in-areas-having-special-flood-hazards",
  "canonical_url": "https://www.federalregister.gov/documents/2015/07/21/2015-15956/loans-in-areas-having-special-flood-hazards",
  "scraped_on": "2026-04-02",
  "enriched_timestamp": "2026-04-02T01:12:39Z",
  "connected_files": {
    "source_html_url": "https://www.federalregister.gov/documents/2015/07/21/2015-15956/loans-in-areas-having-special-flood-hazards",
    "body_html_url": "https://www.federalregister.gov/documents/full_text/html/2015/07/21/2015-15956.html",
    "pdf_source_url": "https://www.govinfo.gov/content/pkg/FR-2015-07-21/pdf/2015-15956.pdf",
    "raw_html_local": "federal_register/raw_html/2015-15956_Loans_in_Areas_Having_Special_Flood_Hazards.html",
    "styled_html_local": "federal_register/html/2015-15956_Loans_in_Areas_Having_Special_Flood_Hazards.html",
    "metadata_json": "federal_register/json/2015-15956_Loans_in_Areas_Having_Special_Flood_Hazards.json",
    "markdown": "federal_register/md/2015-15956_Loans_in_Areas_Having_Special_Flood_Hazards.md",
    "pdf_local": "federal_register/pdf/2015-15956_Loans_in_Areas_Having_Special_Flood_Hazards.pdf"
  },
  "bm25_text": "2015-15956 Loans in Areas Having Special Flood Hazards Final rule. The Office of the Comptroller of the Currency (OCC), Board of Governors of the Federal Reserve System (Board), Federal Deposit Insurance Corporation (FDIC), the Farm Credit Administration (FCA), and t",
  "vector_text_prefix": "Federal Reserve Final Rule 2015-15956: Loans in Areas Having Special Flood Hazards",
  "normalized_text_sha256": "c75c4aa29e9e1c0e640d76a4e1b7cb2a497a13714d7915b9cac7f8904f13b0b4",
  "raw_html_path": "federal_register/raw_html/2015-15956_Loans_in_Areas_Having_Special_Flood_Hazards.html",
  "normalized_md_path": "federal_register/md/2015-15956_Loans_in_Areas_Having_Special_Flood_Hazards.md",
  "canonical_json_path": "federal_register/json/2015-15956_Loans_in_Areas_Having_Special_Flood_Hazards.json",
  "parser_version": "nova-fr-api-v1",
  "normalizer_version": "nova-fr-enricher-v2",
  "quality_score": 100,
  "quality_flags": [],
  "original_effective_date": "2015-07-21",
  "version_sort_key": "2015-10-01"
}