{
  "doc_id": "usfed.fr.E6-14342",
  "doc_family_id": "usfed.fr.E6-14342",
  "title": "Electronic Fund Transfers",
  "short_title": "E6-14342",
  "slug": "E6-14342",
  "title_normalized": "Electronic Fund Transfers",
  "regulator": "Federal Reserve System",
  "regulator_acronym": "FRS",
  "jurisdiction": "United States",
  "document_class": "Final Rule",
  "publication_type": "Final Rule",
  "publication_type_normalized": "Final Rule",
  "authority_class": "primary_normative",
  "authority_level": "binding_regulation",
  "nova_tier": 2,
  "prudential_weight": 0.7,
  "status": "active",
  "heading_path": [
    "Federal Reserve System",
    "Federal Register",
    "Final Rule",
    "E6-14342"
  ],
  "section_path": "Federal Reserve System > Federal Register > Final Rule > E6-14342",
  "structural_level": "document",
  "normative_weight": "mandatory",
  "current_version_flag": true,
  "is_primary_normative": true,
  "is_supporting_interpretive": false,
  "is_context_only": false,
  "paragraph_role": "scope_statement",
  "contains_definition": true,
  "contains_formula": false,
  "contains_requirement": true,
  "contains_deadline": true,
  "contains_parameter": false,
  "contains_assignment": false,
  "is_appendix": false,
  "depth": 0,
  "version_id": "2006-08-30",
  "version_label": "2006",
  "citation_anchor": "#fr-E6-14342",
  "document_number": "E6-14342",
  "citation": "71 FR 51451",
  "publication_date": "2006-08-30",
  "effective_date_start": "2007-01-01",
  "effective_date_end": null,
  "abstract": "The Board is amending Regulation E, which implements the Electronic Fund Transfer Act, and the official staff commentary to the regulation, which interprets the requirements of Regulation E. The amendments clarify that the requirement to obtain a consumer's authorization to collect a service fee for insufficient or uncollected funds through an electronic debit to the consumer's account applies to any person that intends to collect the fee in that manner. The amendments also clarify notice requirements for electronic check conversion transactions and for collecting insufficient funds fees electronically. This interim final rule, for which the Board is seeking comment, will supersede the corresponding provisions of the January 2006 final rule that addressed these topics.",
  "action": "Interim final rule; request for public comment.",
  "html_url": "https://www.federalregister.gov/documents/2006/08/30/E6-14342/electronic-fund-transfers",
  "body_html_url": "https://www.federalregister.gov/documents/full_text/html/2006/08/30/E6-14342.html",
  "pdf_url": "https://www.govinfo.gov/content/pkg/FR-2006-08-30/pdf/E6-14342.pdf",
  "cfr_references": [
    {
      "chapter": null,
      "citation_url": null,
      "part": 205,
      "title": 12
    }
  ],
  "docket_ids": [
    "Regulation E",
    "Docket No. R-1265"
  ],
  "regulation_id_numbers": [],
  "page_length": 7,
  "issuing_agency": "Board of Governors of the Federal Reserve System",
  "issuing_division": "Board of Governors",
  "document_date_iso": "2006-08-30",
  "document_date_raw": "2006-08-30",
  "word_count_raw_body": 7230,
  "section_headings": [],
  "toc_depth": 0,
  "has_appendices": false,
  "has_tables": false,
  "table_count": 0,
  "has_footnotes": false,
  "footnote_count": 0,
  "inline_cross_references": [
    "{'chapter': None, 'citation_url': None, 'part': 205, 'title': 12}"
  ],
  "include_in_primary_corpus": true,
  "include_in_context_corpus": true,
  "include_in_support_corpus": false,
  "applies_to_state_member_banks": false,
  "applies_to_bank_holding_companies": false,
  "applies_to_savings_loan_holding": false,
  "applies_to_foreign_banking_orgs": false,
  "applies_to_nonbank_financial": false,
  "applies_to_insured_depository": true,
  "superseded_by_doc_id": null,
  "supersedes_doc_id": null,
  "correction_of": null,
  "corrections": [],
  "is_correction": false,
  "has_corrections": false,
  "start_page": 51451,
  "end_page": 51457,
  "content_source": "Federal Register API",
  "source_url": "https://www.federalregister.gov/documents/2006/08/30/E6-14342/electronic-fund-transfers",
  "source_html_url": "https://www.federalregister.gov/documents/2006/08/30/E6-14342/electronic-fund-transfers",
  "canonical_url": "https://www.federalregister.gov/documents/2006/08/30/E6-14342/electronic-fund-transfers",
  "scraped_on": "2026-04-02",
  "enriched_timestamp": "2026-04-02T01:16:37Z",
  "connected_files": {
    "source_html_url": "https://www.federalregister.gov/documents/2006/08/30/E6-14342/electronic-fund-transfers",
    "body_html_url": "https://www.federalregister.gov/documents/full_text/html/2006/08/30/E6-14342.html",
    "pdf_source_url": "https://www.govinfo.gov/content/pkg/FR-2006-08-30/pdf/E6-14342.pdf",
    "raw_html_local": "federal_register/raw_html/E6-14342_Electronic_Fund_Transfers.html",
    "styled_html_local": "federal_register/html/E6-14342_Electronic_Fund_Transfers.html",
    "metadata_json": "federal_register/json/E6-14342_Electronic_Fund_Transfers.json",
    "markdown": "federal_register/md/E6-14342_Electronic_Fund_Transfers.md",
    "pdf_local": "federal_register/pdf/E6-14342_Electronic_Fund_Transfers.pdf"
  },
  "bm25_text": "E6-14342 Electronic Fund Transfers Interim final rule; request for public comment. The Board is amending Regulation E, which implements the Electronic Fund Transfer Act, and the official staff commentary to the regulation, which interprets the requirements of Regulation E. The amend",
  "vector_text_prefix": "Federal Reserve Final Rule E6-14342: Electronic Fund Transfers",
  "normalized_text_sha256": "8142d1c8f2490c918d20d08f342cbf6dab98d7c1bb30a20c87add15ff0deb5cc",
  "raw_html_path": "federal_register/raw_html/E6-14342_Electronic_Fund_Transfers.html",
  "normalized_md_path": "federal_register/md/E6-14342_Electronic_Fund_Transfers.md",
  "canonical_json_path": "federal_register/json/E6-14342_Electronic_Fund_Transfers.json",
  "parser_version": "nova-fr-api-v1",
  "normalizer_version": "nova-fr-enricher-v2",
  "quality_score": 100,
  "quality_flags": [],
  "original_effective_date": "2006-08-30",
  "version_sort_key": "2007-01-01"
}