{
  "doc_id": "usfed.sr90-8.19900222.letter",
  "title": "SR 90-8: FRB: Supervisory Letter SR 90-8 (SA) on inspection procedures for \"Section 20 Subsidiaries\" -- February 22, 1990",
  "title_normalized": "FRB: Supervisory Letter SR 90-8 (SA) on inspection procedures for \"Section 20 Subsidiaries\" -- February 22, 1990",
  "short_title": "SR 90-8",
  "slug": "sr-letter-sr90-8",
  "regulator": "Federal Reserve System",
  "regulator_acronym": "FRS",
  "jurisdiction": "United States",
  "document_class": "examination_guidance",
  "publication_type": "SR Letter",
  "publication_type_normalized": "sr_letter",
  "nova_tier": 2,
  "authority_class": "reference_interpretive",
  "authority_level": "supervisory_guidance",
  "prudential_weight": 0.5,
  "status": "active",
  "current_version_flag": true,
  "is_primary_normative": false,
  "is_supporting_interpretive": true,
  "is_context_only": false,
  "sr_letter_number": "SR 90-8",
  "sr_year": 1990,
  "sr_sequence": 8,
  "section_path": "Federal Reserve System > Supervision and Regulation > SR Letters > SR 90-8",
  "citation_anchor": "#srsr90-8",
  "issuing_agency": "Board of Governors of the Federal Reserve System",
  "issuing_division": "Division of Supervision and Regulation",
  "document_date_raw": "February 22, 1990",
  "document_date_iso": "1990-02-22",
  "effective_date_start": "1990-02-22",
  "effective_date_end": null,
  "scraped_on": "2026-03-26",
  "enriched_timestamp": "2026-03-31T14:37:45Z",
  "applicability_raw": "",
  "applies_to_state_member_banks": false,
  "applies_to_bank_holding_companies": true,
  "applies_to_savings_loan_holding": false,
  "applies_to_foreign_banking_orgs": true,
  "applies_to_nonbank_financial": false,
  "applies_to_edge_agreement_corps": false,
  "applies_to_large_institutions": false,
  "word_count_raw_body": 426,
  "section_headings": [
    "BOARD OF GOVERNORSOF THEFEDERAL RESERVE SYSTEMWASHINGTON, D. C.  20551",
    "DIVISION OF BANKINGSUPERVISION AND REGULATION",
    "TO THE OFFICER IN CHARGE OF SUPERVISION",
    "AT EACH FEDERAL RESERVE BANK",
    "SUBJECT:"
  ],
  "toc_depth": 5,
  "has_appendices": false,
  "has_tables": false,
  "table_count": 0,
  "has_footnotes": false,
  "footnote_count": 0,
  "inline_cross_references": [
    "SR 90-8"
  ],
  "content_source": "Federal Reserve Website",
  "source_url": "https://www.federalreserve.gov/boarddocs/srletters/1990/SR9008.HTM",
  "canonical_url": "https://www.federalreserve.gov/boarddocs/srletters/1990/SR9008.HTM",
  "normalized_text_sha256": "d4ebc2df7971883c79f0995b9b83f01a056b1bfbd17b230748d63b17b1e752ab",
  "normalized_md_path": "SR_Letters/md/SR_90-8_Inspection_Procedures_For_Section_20_Subsidiaries.md",
  "canonical_json_path": "SR_Letters/json/SR_90-8_Inspection_Procedures_For_Section_20_Subsidiaries.json",
  "parser_version": "nova-sr-scraper-v1",
  "normalizer_version": "nova-sr-enricher-v1",
  "include_in_primary_corpus": true,
  "include_in_context_corpus": true,
  "include_in_support_corpus": true,
  "quality_score": 85,
  "quality_flags": [
    "missing_applicability"
  ],
  "superseded_by_doc_id": null,
  "supersedes_doc_id": null,
  "bm25_text": "SR 90-8 FRB: Supervisory Letter SR 90-8 (SA) on inspection procedures for \"Section 20 Subsidiaries\" -- February 22, 1990  BOARD OF GOVERNORSOF THEFEDERAL RESERVE SYSTEMWASHINGTON, D. C.  20551 DIVISION OF BANKINGSUPERVISION AND REGULATION TO THE OFFICER IN CHARGE OF SUPERVISION AT EACH FEDERAL RESERVE BANK SUBJECT:",
  "vector_text_prefix": "Federal Reserve SR Letter SR 90-8: FRB: Supervisory Letter SR 90-8 (SA) on inspection procedures for \"Section 20 Subsidiaries\" -- February 22, 1990",
  "heading_path": [
    "Federal Reserve System",
    "Supervision and Regulation",
    "SR Letters",
    "SR 90-8"
  ],
  "structural_level": "document",
  "normative_weight": "advisory",
  "paragraph_role": "scope_statement",
  "doc_family_id": "usfed.sr90-8",
  "contains_definition": false,
  "contains_requirement": false,
  "version_id": "1990-02-22",
  "version_label": "1990"
}