{
  "doc_id": "usfed.regff.232.20260309.part",
  "doc_family_id": "usfed.regff.232",
  "title": "Regulation FF: OBTAINING AND USING MEDICAL INFORMATION IN CONNECTION WITH CREDIT",
  "short_title": "Reg FF",
  "slug": "12cfr-part-232",
  "title_normalized": "OBTAINING AND USING MEDICAL INFORMATION IN CONNECTION WITH CREDIT",
  "regulator": "Federal Reserve System",
  "regulator_acronym": "FRS",
  "jurisdiction": "United States",
  "document_class": "federal_regulation",
  "publication_type": "eCFR Regulation",
  "publication_type_normalized": "ecfr_regulation",
  "authority_class": "primary_normative",
  "authority_level": "binding_regulation",
  "nova_tier": 3,
  "prudential_weight": 0.4,
  "status": "active",
  "heading_path": [
    "Federal Reserve System",
    "12 CFR Chapter II",
    "Regulation FF",
    "Part 232"
  ],
  "section_path": "Federal Reserve System > 12 CFR Chapter II > Regulation FF > Part 232",
  "structural_level": "part",
  "normative_weight": "mandatory",
  "current_version_flag": true,
  "is_primary_normative": true,
  "is_supporting_interpretive": false,
  "is_context_only": false,
  "paragraph_role": "scope_statement",
  "contains_definition": true,
  "contains_formula": false,
  "contains_requirement": false,
  "contains_deadline": false,
  "contains_parameter": true,
  "contains_assignment": false,
  "is_appendix": false,
  "depth": 1,
  "version_id": "2017-01-24",
  "version_label": "2026",
  "citation_anchor": "#12cfr232",
  "title_number": 12,
  "title_name": "Banks and Banking",
  "chapter": "II",
  "chapter_name": "Federal Reserve System",
  "part_number": 232,
  "part_name": "PART 232—OBTAINING AND USING MEDICAL INFORMATION IN CONNECTION WITH CREDIT (REGULATION FF)",
  "regulation_letter": "FF",
  "regulation_name": "OBTAINING AND USING MEDICAL INFORMATION IN CONNECTION WITH CREDIT",
  "cfr_citation": "12 CFR Part 232",
  "authority": "15 U.S.C. 1681b .",
  "source": "70 FR 70682 , Nov. 22, 2005, unless otherwise noted.",
  "issuing_agency": "Board of Governors of the Federal Reserve System",
  "issuing_division": "Board of Governors",
  "ecfr_current_as_of": "2026-03-09",
  "effective_date_start": "2017-01-24",
  "effective_date_end": null,
  "original_effective_date": "2016-12-27",
  "scraped_on": "2026-04-02",
  "enriched_timestamp": "2026-04-02T00:43:57Z",
  "superseded_by_doc_id": null,
  "supersedes_doc_id": null,
  "section_count": 4,
  "appendix_count": 0,
  "word_count_raw_body": 3436,
  "section_headings": [
    "§ 232.1 Scope, general prohibition and definitions.",
    "§ 232.2 Rule of construction for obtaining and using unsolicited medical information.",
    "§ 232.3 Financial information exception for obtaining and using medical information.",
    "§ 232.4 Specific exceptions for obtaining and using medical information."
  ],
  "toc_depth": 1,
  "has_appendices": false,
  "has_tables": false,
  "table_count": 0,
  "has_footnotes": false,
  "footnote_count": 0,
  "inline_cross_references": [
    "12 CFR Part 232",
    "Regulation FF",
    "§ 232.1",
    "§ 232.2",
    "§ 232.3",
    "§ 232.4",
    "§ 41.30"
  ],
  "include_in_primary_corpus": false,
  "include_in_context_corpus": true,
  "include_in_support_corpus": false,
  "applies_to_state_member_banks": true,
  "applies_to_bank_holding_companies": false,
  "applies_to_savings_loan_holding": false,
  "applies_to_foreign_banking_orgs": false,
  "applies_to_edge_agreement_corps": false,
  "applies_to_nonbank_financial": false,
  "content_source": "eCFR API",
  "source_url": "https://www.ecfr.gov/current/title-12/chapter-II/part-232",
  "source_api_url": "https://www.ecfr.gov/api/renderer/v1/content/enhanced/2026-03-09/title-12?part=232",
  "canonical_url": "https://www.ecfr.gov/current/title-12/chapter-II/part-232",
  "connected_files": {
    "source_url": "https://www.ecfr.gov/current/title-12/chapter-II/part-232",
    "source_api_url": "https://www.ecfr.gov/api/renderer/v1/content/enhanced/2026-03-09/title-12?part=232",
    "raw_html_local": "ecfr/raw_html/Reg_FF_OBTAINING_AND_USING_MEDICAL_INFORMATION_IN_CONNECTION_WITH_CREDIT_12CFR232.html",
    "styled_html_local": "ecfr/html/Reg_FF_OBTAINING_AND_USING_MEDICAL_INFORMATION_IN_CONNECTION_WITH_CREDIT_12CFR232.html",
    "metadata_json": "ecfr/json/Reg_FF_OBTAINING_AND_USING_MEDICAL_INFORMATION_IN_CONNECTION_WITH_CREDIT_12CFR232.json",
    "markdown": "ecfr/md/Reg_FF_OBTAINING_AND_USING_MEDICAL_INFORMATION_IN_CONNECTION_WITH_CREDIT_12CFR232.md",
    "pdf_local": "ecfr/pdf/Reg_FF_OBTAINING_AND_USING_MEDICAL_INFORMATION_IN_CONNECTION_WITH_CREDIT_12CFR232.pdf"
  },
  "bm25_text": "Reg FF Regulation FF: OBTAINING AND USING MEDICAL INFORMATION IN CONNECTION WITH CREDIT 12cfr part 232 § 232.1 Scope, general prohibition and definitions. § 232.2 Rule of construction for obtaining and using unsolicited medical information. § 232.3 Financial information exception for obtaining and using medical information. § 232.4 Specific exceptions for obtaining and using medical information.",
  "vector_text_prefix": "US Federal Reserve 12 CFR Part 232 Reg FF: Regulation FF: OBTAINING AND USING MEDICAL INFORMATION IN CONNECTION WITH CREDIT",
  "normalized_text_sha256": "c5bbe34c466bba3d0f4d2d1d969a06a33559459f1ee8d92c25ffc1e960b6bfb6",
  "raw_html_path": "ecfr/raw_html/Reg_FF_OBTAINING_AND_USING_MEDICAL_INFORMATION_IN_CONNECTION_WITH_CREDIT_12CFR232.html",
  "normalized_md_path": "ecfr/md/Reg_FF_OBTAINING_AND_USING_MEDICAL_INFORMATION_IN_CONNECTION_WITH_CREDIT_12CFR232.md",
  "canonical_json_path": "ecfr/json/Reg_FF_OBTAINING_AND_USING_MEDICAL_INFORMATION_IN_CONNECTION_WITH_CREDIT_12CFR232.json",
  "parser_version": "nova-ecfr-scraper-v1",
  "normalizer_version": "nova-ecfr-enricher-v2",
  "quality_score": 100,
  "quality_flags": [],
  "amendment_count": 2,
  "amendment_dates": [
    "2016-12-27",
    "2017-01-24"
  ],
  "version_sort_key": "2017-01-24"
}