{
  "doc_id": "usfed.regm.213.20260309.part",
  "doc_family_id": "usfed.regm.213",
  "title": "Regulation M: CONSUMER LEASING",
  "short_title": "Reg M",
  "slug": "12cfr-part-213",
  "title_normalized": "CONSUMER LEASING",
  "regulator": "Federal Reserve System",
  "regulator_acronym": "FRS",
  "jurisdiction": "United States",
  "document_class": "federal_regulation",
  "publication_type": "eCFR Regulation",
  "publication_type_normalized": "ecfr_regulation",
  "authority_class": "primary_normative",
  "authority_level": "binding_regulation",
  "nova_tier": 3,
  "prudential_weight": 0.4,
  "status": "active",
  "heading_path": [
    "Federal Reserve System",
    "12 CFR Chapter II",
    "Regulation M",
    "Part 213"
  ],
  "section_path": "Federal Reserve System > 12 CFR Chapter II > Regulation M > Part 213",
  "structural_level": "part",
  "normative_weight": "mandatory",
  "current_version_flag": true,
  "is_primary_normative": true,
  "is_supporting_interpretive": false,
  "is_context_only": false,
  "paragraph_role": "scope_statement",
  "contains_definition": true,
  "contains_formula": false,
  "contains_requirement": true,
  "contains_deadline": false,
  "contains_parameter": true,
  "contains_assignment": false,
  "is_appendix": false,
  "depth": 1,
  "version_id": "2026-01-01",
  "version_label": "2026",
  "citation_anchor": "#12cfr213",
  "title_number": 12,
  "title_name": "Banks and Banking",
  "chapter": "II",
  "chapter_name": "Federal Reserve System",
  "part_number": 213,
  "part_name": "PART 213—CONSUMER LEASING (REGULATION M)",
  "regulation_letter": "M",
  "regulation_name": "CONSUMER LEASING",
  "cfr_citation": "12 CFR Part 213",
  "authority": "15 U.S.C. 1604 and 1667f ; Pub. L. No. 111-203 section 1100E, 124 Stat. 1376.",
  "source": "Reg. M, 61 FR 52258 , Oct. 7, 1996, unless otherwise noted.",
  "issuing_agency": "Board of Governors of the Federal Reserve System",
  "issuing_division": "Board of Governors",
  "ecfr_current_as_of": "2026-03-09",
  "effective_date_start": "2026-01-01",
  "effective_date_end": null,
  "original_effective_date": "2017-01-01",
  "scraped_on": "2026-04-02",
  "enriched_timestamp": "2026-04-02T00:42:09Z",
  "superseded_by_doc_id": null,
  "supersedes_doc_id": null,
  "section_count": 9,
  "appendix_count": 4,
  "word_count_raw_body": 15901,
  "section_headings": [
    "§ 213.1 Authority, scope, purpose, and enforcement.",
    "§ 213.2 Definitions.",
    "§ 213.3 General disclosure requirements.",
    "§ 213.4 Content of disclosures.",
    "§ 213.5 Renegotiations, extensions, and assumptions.",
    "§ 213.6 [Reserved]",
    "§ 213.7 Advertising.",
    "§ 213.8 Record retention.",
    "§ 213.9 Relation to state laws."
  ],
  "toc_depth": 1,
  "has_appendices": true,
  "has_tables": false,
  "table_count": 0,
  "has_footnotes": false,
  "footnote_count": 0,
  "inline_cross_references": [
    "12 CFR 226",
    "12 CFR Part 213",
    "Regulation M",
    "Regulation Z",
    "§ 213.1",
    "§ 213.2",
    "§ 213.3",
    "§ 213.4",
    "§ 213.7"
  ],
  "include_in_primary_corpus": false,
  "include_in_context_corpus": true,
  "include_in_support_corpus": false,
  "applies_to_state_member_banks": true,
  "applies_to_bank_holding_companies": false,
  "applies_to_savings_loan_holding": false,
  "applies_to_foreign_banking_orgs": false,
  "applies_to_edge_agreement_corps": false,
  "applies_to_nonbank_financial": false,
  "content_source": "eCFR API",
  "source_url": "https://www.ecfr.gov/current/title-12/chapter-II/part-213",
  "source_api_url": "https://www.ecfr.gov/api/renderer/v1/content/enhanced/2026-03-09/title-12?part=213",
  "canonical_url": "https://www.ecfr.gov/current/title-12/chapter-II/part-213",
  "connected_files": {
    "source_url": "https://www.ecfr.gov/current/title-12/chapter-II/part-213",
    "source_api_url": "https://www.ecfr.gov/api/renderer/v1/content/enhanced/2026-03-09/title-12?part=213",
    "raw_html_local": "ecfr/raw_html/Reg_M_CONSUMER_LEASING_12CFR213.html",
    "styled_html_local": "ecfr/html/Reg_M_CONSUMER_LEASING_12CFR213.html",
    "metadata_json": "ecfr/json/Reg_M_CONSUMER_LEASING_12CFR213.json",
    "markdown": "ecfr/md/Reg_M_CONSUMER_LEASING_12CFR213.md",
    "pdf_local": "ecfr/pdf/Reg_M_CONSUMER_LEASING_12CFR213.pdf"
  },
  "bm25_text": "Reg M Regulation M: CONSUMER LEASING 12cfr part 213 § 213.1 Authority, scope, purpose, and enforcement. § 213.2 Definitions. § 213.3 General disclosure requirements. § 213.4 Content of disclosures. § 213.5 Renegotiations, extensions, and assumptions. § 213.6 [Reserved] § 213.7 Advertising. § 213.8 Record retention. § 213.9 Relation to state laws.",
  "vector_text_prefix": "US Federal Reserve 12 CFR Part 213 Reg M: Regulation M: CONSUMER LEASING",
  "normalized_text_sha256": "6971d6939127ae832d929694fd456631aa9df6993645864cd86b5f55e15818af",
  "raw_html_path": "ecfr/raw_html/Reg_M_CONSUMER_LEASING_12CFR213.html",
  "normalized_md_path": "ecfr/md/Reg_M_CONSUMER_LEASING_12CFR213.md",
  "canonical_json_path": "ecfr/json/Reg_M_CONSUMER_LEASING_12CFR213.json",
  "parser_version": "nova-ecfr-scraper-v1",
  "normalizer_version": "nova-ecfr-enricher-v2",
  "quality_score": 100,
  "quality_flags": [],
  "amendment_count": 19,
  "amendment_dates": [
    "2024-01-01",
    "2024-10-15",
    "2025-01-01",
    "2025-12-15",
    "2026-01-01"
  ],
  "version_sort_key": "2026-01-01"
}